README.rst
setup.py
pyrogi/__init__.py
pyrogi/core.py
pyrogi/events.py
pyrogi/pygame_core.py
pyrogi/test_core.py
pyrogi/test_events.py
pyrogi.egg-info/PKG-INFO
pyrogi.egg-info/SOURCES.txt
pyrogi.egg-info/dependency_links.txt
pyrogi.egg-info/requires.txt
pyrogi.egg-info/top_level.txt
pyrogi/drawing/__init__.py
pyrogi/drawing/drawing.py
pyrogi/drawing/paints.py
pyrogi/drawing/pygame_graphics.py
pyrogi/drawing/test_drawing.py
pyrogi/ui/__init__.py
pyrogi/ui/elements.py
pyrogi/ui/ui.py
pyrogi/util/__init__.py
pyrogi/util/test_vector.py
pyrogi/util/vector.py